aotycount.py
aotycount-0.1.2.dist-info/METADATA
aotycount-0.1.2.dist-info/WHEEL
aotycount-0.1.2.dist-info/entry_points.txt
aotycount-0.1.2.dist-info/RECORD
