Metadata-Version: 2.4
Name: aotycount
Version: 0.1.2
Summary: Summarize the album's on Alf Eaton's AOTY site
Author-email: Ed Summers <ehs@pobox.com>
Requires-Python: >=3.11
Requires-Dist: beautifulsoup4>=4.12.2
Requires-Dist: requests>=2.31.0
